easyclimate_rust-2026.1.0.dist-info/METADATA
easyclimate_rust-2026.1.0.dist-info/WHEEL
easyclimate_rust-2026.1.0.dist-info/licenses/LICENSE
easyclimate_rust/__init__.py
easyclimate_rust/_easyclimate_rust.cpython-312-x86_64-linux-gnu.so
easyclimate_rust-2026.1.0.dist-info/RECORD
