Metadata-Version: 2.4
Name: easyclimate_rust
Version: 2026.1.0
Classifier: Programming Language :: Python
Classifier: Programming Language :: Python :: 3
Classifier: Programming Language :: Python :: 3.10
Classifier: Programming Language :: Python :: 3.11
Classifier: Programming Language :: Python :: 3.12
Classifier: Programming Language :: Python :: 3.13
Classifier: Programming Language :: Python :: 3.14
Classifier: Programming Language :: Python :: 3 :: Only
Classifier: Topic :: Scientific/Engineering
Classifier: Operating System :: Microsoft :: Windows
Classifier: Operating System :: POSIX
Classifier: Operating System :: Unix
Classifier: Programming Language :: Rust
Classifier: Programming Language :: Python :: Implementation :: CPython
License-File: LICENSE
Summary: The rust backend of easyclimate
Author: shenyulu
Requires-Python: >=3.10
Project-URL: homepage, https://github.com/shenyulu/easyclimate-rust
Project-URL: documentation, https://github.com/shenyulu/easyclimate-rust
Project-URL: source, https://github.com/shenyulu/easyclimate-rust
Project-URL: download, https://pypi.org/project/easyclimate-rust/#files
Project-URL: tracker, https://github.com/shenyulu/easyclimate-rust/issues
